MANIFEST.in
README.md
VERSION
manage.py
requirements.txt
setup.cfg
setup.py
djotali/__init__.py
djotali/celery.py
djotali/conftest.py
djotali/urls.py
djotali/wsgi.py
djotali.egg-info/PKG-INFO
djotali.egg-info/SOURCES.txt
djotali.egg-info/dependency_links.txt
djotali.egg-info/requires.txt
djotali.egg-info/top_level.txt
djotali/billing/__init__.py
djotali/billing/admin.py
djotali/billing/apps.py
djotali/billing/exceptions.py
djotali/billing/middleware.py
djotali/billing/models.py
djotali/billing/signals.py
djotali/billing/urls.py
djotali/billing/views.py
djotali/billing/migrations/0001_initial.py
djotali/billing/migrations/__init__.py
djotali/campaigns/__init__.py
djotali/campaigns/admin.py
djotali/campaigns/apps.py
djotali/campaigns/forms.py
djotali/campaigns/models.py
djotali/campaigns/signals.py
djotali/campaigns/tasks.py
djotali/campaigns/urls.py
djotali/campaigns/views.py
djotali/campaigns/widgets.py
djotali/campaigns/api/__init__.py
djotali/campaigns/api/serializers.py
djotali/campaigns/api/urls.py
djotali/campaigns/api/viewsets.py
djotali/campaigns/migrations/0001_initial.py
djotali/campaigns/migrations/__init__.py
djotali/campaigns/templatetags/__init__.py
djotali/campaigns/templatetags/campaigns_extras.py
djotali/contacts/__init__.py
djotali/contacts/admin.py
djotali/contacts/apps.py
djotali/contacts/forms.py
djotali/contacts/groups_urls.py
djotali/contacts/models.py
djotali/contacts/signals.py
djotali/contacts/tasks.py
djotali/contacts/urls.py
djotali/contacts/views.py
djotali/contacts/widgets.py
djotali/contacts/csv/__init__.py
djotali/contacts/csv/models.py
djotali/contacts/csv/utils.py
djotali/contacts/migrations/0001_initial.py
djotali/contacts/migrations/__init__.py
djotali/contacts/templatetags/__init__.py
djotali/contacts/templatetags/contacts_extras.py
djotali/core/__init__.py
djotali/core/admin.py
djotali/core/apps.py
djotali/core/context_processors.py
djotali/core/forms.py
djotali/core/models.py
djotali/core/urls.py
djotali/core/utils.py
djotali/core/views.py
djotali/core/widgets.py
djotali/core/management/__init__.py
djotali/core/management/commands/__init__.py
