Metadata-Version: 1.0
Name: djotali
Version: 1.0.0rc11
Summary: Our SAAS solution to easily send messages to your clients
Home-page: UNKNOWN
Author: Pascal Ekouaghe
Author-email: ekougs@gmail.com
License: MIT
Platform: UNKNOWN
